assembly_emulator/__init__.py
assembly_emulator/asm8086_demo.py
assembly_emulator/test_asm.py
assembly_emulator-1.0.4.dist-info/LICENSE
assembly_emulator-1.0.4.dist-info/METADATA
assembly_emulator-1.0.4.dist-info/WHEEL
assembly_emulator-1.0.4.dist-info/top_level.txt
assembly_emulator-1.0.4.dist-info/RECORD
