Metadata-Version: 2.1
Name: assembly-emulator
Version: 1.0.4
Summary: Emulate basic Lisp environment in python3 for educational reasons.
Author: jonaprojects
Classifier: Programming Language :: Python :: 3
License-File: LICENSE
Requires-Dist: pyfiglet
